reflectance/RS_info_dictionaries.json
reflectance/RS_info_templates.py
reflectance/__init__.py
reflectance/colour_circle.png
reflectance/databases.py
reflectance/db_config.json
reflectance/plotting.py
reflectance/process_rawfiles.py
reflectance/reflectance.py
reflectance-0.1.0.dist-info/LICENSE
reflectance-0.1.0.dist-info/METADATA
reflectance-0.1.0.dist-info/WHEEL
reflectance-0.1.0.dist-info/top_level.txt
reflectance-0.1.0.dist-info/RECORD
