Metadata-Version: 2.2
Name: reflectance
Version: 0.1.0
Summary: Package to manipulate reflectance data
Author: Gauthier Patin
Author-email: Gauthier Patin <g.patin@monemail.com>
License:                     GNU GENERAL PUBLIC LICENSE
Project-URL: Homepage, https://github.com/g-patin/reflectance
Keywords: reflectance spectroscopy,colour measurement
Classifier: Programming Language :: Python :: 3
Classifier: License :: OSI Approved :: GNU General Public License v3 (GPLv3)
Classifier: Operating System :: OS Independent
Requires-Python: >=3.8
License-File: LICENSE
Requires-Dist: colour-science
Requires-Dist: seaborn
Requires-Dist: uncertainties
Requires-Dist: matplotlib
Requires-Dist: pandas
Requires-Dist: openpyxl
Requires-Dist: jupyterlab
Requires-Dist: xarray
Requires-Dist: ipywidgets
